pynuxmv/__init__.py
pynuxmv/cli.py
pynuxmv/main.py
pynuxmv/optimizations.py
pynuxmv/pyomy.py
pynuxmv/templates.py
pynuxmv-0.1.2.dist-info/METADATA
pynuxmv-0.1.2.dist-info/WHEEL
pynuxmv-0.1.2.dist-info/entry_points.txt
pynuxmv-0.1.2.dist-info/top_level.txt
pynuxmv-0.1.2.dist-info/RECORD
