Metadata-Version: 2.1
Name: pynuxmv
Version: 0.1.2
Summary: Transpile Python to nuXmv source code
Home-page: https://github.com/mattyonweb/pynuxmv
Author: Matteo Cavada
Author-email: cvd00@insicuri.net
License: UNKNOWN
Platform: UNKNOWN
Classifier: Development Status :: 2 - Pre-Alpha
Classifier: Operating System :: POSIX :: Linux
Classifier: Programming Language :: Python :: 3.8
Classifier: Topic :: Software Development :: Testing
Requires-Python: >=3.8
Provides-Extra: pretty_printing
Requires-Dist: astpretty ; extra == 'pretty_printing'
